Workbook

Sheet Overview
A1: CenterWell (a Humana Inc. company) — Executive Profile
A2: Prepared Oct 1, 2026 from Humana SEC filings & earnings releases. See 'Sources' tab. $ in millions unless noted.
A4: Attribute | B4: Detail
A5: Parent company | B5: Humana Inc. (NYSE: HUM), Louisville, KY
A6: What CenterWell is | B6: Humana's payer-agnostic healthcare services arm: pharmacy (excl. PBM), senior primary care, and home solutions. Serves patients on many health plans, not only Humana.
A7: Reporting segment | B7: One of Humana's two reportable segments (Insurance + CenterWell). Formerly 'Healthcare Services'; realigned Dec 2022.
A8: Brand launch | B8: March 16, 2021 (CenterWell Senior Primary Care first). Pharmacy rebranded Jun 2022 (CenterWell Pharmacy / CenterWell Specialty Pharmacy); Kindred at Home's home health division became CenterWell Home Health during 2022.
A9: Brand positioning / 'motto' | B9: Official brand statement: care experiences that put patients at the center. Humana's corporate purpose: 'putting health first'. No separate trademarked CenterWell slogan found in filings.
A10: Logo meaning | B10: Blossom with three petals = physical, emotional and social wellness (whole-person health).
A11: Humana CEO | B11: Jim Rechtin (President & CEO)
A12: Business lines | B12: 1) Pharmacy Solutions – CenterWell Pharmacy (mail order), CenterWell Specialty Pharmacy 2) Primary Care – CenterWell Senior Primary Care, Conviva, IPA business 3) Home Solutions – CenterWell Home Health
A13: FY2025 segment revenue | B13: 22473
A14: FY2025 income from operations | B14: 1339
A15: FY2026 revenue guidance | B15: At least $25 billion (affirmed Jul 29, 2026)
A16: FY2026 IFO guidance | B16: GAAP $1.3B–$1.8B; Adjusted (adds back D&A) $1.5B–$2.0B
A17: Primary care footprint (Jun 30, 2026) | B17: 398 centers · 1,478 primary care providers · ~622,000 patients
A18: Key recent deals | B18: Kindred at Home (full acquisition, Apr 2021); divested 60% of Gentiva Hospice (Aug 2022); The Villages Health (closed Nov 2025, ~32k patients, 8 centers); MaxHealth (Q1 2026).
A19: Key headwinds | B19: CMS v28 risk-model phase-in (2026 = final year) pressuring primary care margins; higher-cost-ratio specialty pharmacy mix; home health reimbursement pressure.

Sheet Financials
A1: CenterWell Segment Financials, FY2021 – FY2026
A2: Blue = reported inputs (Humana 10-K / earnings releases); black = formulas. Segment revenue includes intersegment sales to Humana Insurance.
A4: Metric ($mm) | B4: FY2021 | C4: FY2022 | D4: FY2023 | E4: FY2024 | F4: FY2025 | G4: 1H 2025 | H4: 1H 2026 | I4: FY2026 Guide (low)
A5: Total segment revenue | B5: 14054 | C5: 17299 | D5: 18405 | E5: 19936 | F5: 22473 | G5: 10632 | H5: 12890 | I5: 25000
A6: of which: external services revenue | B6: =B5-B7 -> 2202 | C6: 3926 | D6: 3033 | E6: 3465 | F6: 4816 | G6: 2276 | H6: 3009 | I6: n/a
A7: of which: intersegment (from Humana) | B7: 11852 | C7: 13373 | D7: 15372 | E7: 16471 | F7: 17657 | G7: 8356 | H7: 9881 | I7: n/a
A8: Income from operations (GAAP) | B8: 938 | C8: 1291 | D8: 1404 | E8: 1329 | F8: 1339 | G8: 736 | H8: 755 | I8: 1300
A9: Depreciation & amortization | B9: n/a | C9: n/a | D9: n/a | E9: 224 | F9: 219 | G9: 119 | H9: 97 | I9: n/a
A10: Operating cost ratio (reported) | B10: 0.923 | C10: 0.915 | D10: n/a | E10: 0.922 | F10: 0.931 | G10: 0.92 | H10: 0.934 | I10: n/a
A11: Total operating spend (Revenue − IFO) | B11: =B5-B8 -> 13116 | C11: =C5-C8 -> 16008 | D11: =D5-D8 -> 17001 | E11: =E5-E8 -> 18607 | F11: =F5-F8 -> 21134 | G11: =G5-G8 -> 9896 | H11: =H5-H8 -> 12135 | I11: =I5-I8 -> 23700
A12: Adjusted IFO (IFO + D&A) | B12: =IF(ISNUMBER(B9),B8+B9,"n/a") -> n/a | C12: =IF(ISNUMBER(C9),C8+C9,"n/a") -> n/a | D12: =IF(ISNUMBER(D9),D8+D9,"n/a") -> n/a | E12: =IF(ISNUMBER(E9),E8+E9,"n/a") -> 1553 | F12: =IF(ISNUMBER(F9),F8+F9,"n/a") -> 1558 | G12: =IF(ISNUMBER(G9),G8+G9,"n/a") -> 855 | H12: =IF(ISNUMBER(H9),H8+H9,"n/a") -> 852 | I12: =IF(ISNUMBER(I9),I8+I9,"n/a") -> n/a
A13: Operating margin (IFO ÷ Revenue) | B13: =B8/B5 -> 0.066742564 | C13: =C8/C5 -> 0.074628591 | D13: =D8/D5 -> 0.076283619 | E13: =E8/E5 -> 0.066663323 | F13: =F8/F5 -> 0.05958261 | G13: =G8/G5 -> 0.069224981 | H13: =H8/H5 -> 0.058572537 | I13: =I8/I5 -> 0.052
A14: Adjusted (EBITDA-style) margin | B14: =IF(ISNUMBER(B12),B12/B5,"n/a") -> n/a | C14: =IF(ISNUMBER(C12),C12/C5,"n/a") -> n/a | D14: =IF(ISNUMBER(D12),D12/D5,"n/a") -> n/a | E14: =IF(ISNUMBER(E12),E12/E5,"n/a") -> 0.077899278 | F14: =IF(ISNUMBER(F12),F12/F5,"n/a") -> 0.069327638 | G14: =IF(ISNUMBER(G12),G12/G5,"n/a") -> 0.080417607 | H14: =IF(ISNUMBER(H12),H12/H5,"n/a") -> 0.06609775 | I14: =IF(ISNUMBER(I12),I12/I5,"n/a") -> n/a
A15: Intersegment dependence (% of rev from Humana) | B15: =IF(ISNUMBER(B7),B7/B5,"n/a") -> 0.84331863 | C15: =IF(ISNUMBER(C7),C7/C5,"n/a") -> 0.77305047 | D15: =IF(ISNUMBER(D7),D7/D5,"n/a") -> 0.83520782 | E15: =IF(ISNUMBER(E7),E7/E5,"n/a") -> 0.82619382 | F15: =IF(ISNUMBER(F7),F7/F5,"n/a") -> 0.78569839 | G15: =IF(ISNUMBER(G7),G7/G5,"n/a") -> 0.78592927 | H15: =IF(ISNUMBER(H7),H7/H5,"n/a") -> 0.76656323 | I15: =IF(ISNUMBER(I7),I7/I5,"n/a") -> n/a
A16: Revenue YoY growth | B16: n/a | C16: =C5/B5-1 -> 0.23089512 | D16: =D5/C5-1 -> 0.063934331 | E16: =E5/D5-1 -> 0.083183917 | F16: =F5/E5-1 -> 0.12725722 | G16: n/a | H16: =H5/G5-1 -> 0.21237773 | I16: =I5/F5-1 -> 0.11244605
A17: IFO YoY growth | B17: n/a | C17: =C8/B8-1 -> 0.37633262 | D17: =D8/C8-1 -> 0.087529047 | E17: =E8/D8-1 -> -0.053418803 | F17: =F8/E8-1 -> 0.0075244545 | G17: n/a | H17: =H8/G8-1 -> 0.025815217 | I17: =I8/F8-1 -> -0.029126214
A20: Notes:
A21: • FY2026 Guide column = low end of guidance (revenue 'at least $25B'; GAAP IFO $1.3B–$1.8B). YoY for guide column is vs FY2025. 1H 2026 YoY is vs 1H 2025.
A22: • FY2021 external services revenue derived as total less intersegment. FY2023 operating cost ratio not captured in sources reviewed (n/a).
A23: • Operating cost ratio as reported by Humana excludes D&A. 'Operating spend' = revenue minus GAAP IFO (includes D&A).
A24: • CenterWell is a segment, not a standalone filer: no segment-level net income, tax or interest is disclosed; operating margin is the best profit measure.
A25: • FY2022 services jump reflects full-year Kindred at Home consolidation; FY2023 dip reflects Gentiva Hospice divestiture (Aug 2022).

Sheet Revenue by Line
A1: Revenue by Business Line (incl. intersegment)
A2: Source: Humana statistical supplements (S-12). $ in millions.
A4: Business line | B4: FY2024 | C4: FY2025 | D4: YoY % | E4: 1H 2025 | F4: 1H 2026 | G4: YoY % | H4: FY2025 mix %
A5: Pharmacy Solutions | B5: 11628 | C5: 12959 | D5: =C5/B5-1 -> 0.11446508 | E5: 5979 | F5: 6945 | G5: =F5/E5-1 -> 0.16156548 | H5: =C5/C$8 -> 0.57664753
A6: Primary Care | B6: 4945 | C6: 5986 | D6: =C6/B6-1 -> 0.21051567 | E6: 2898 | F6: 3930 | G6: =F6/E6-1 -> 0.35610766 | H6: =C6/C$8 -> 0.26636408
A7: Home Solutions | B7: 3363 | C7: 3528 | D7: =C7/B7-1 -> 0.049063336 | E7: 1755 | F7: 2015 | G7: =F7/E7-1 -> 0.14814815 | H7: =C7/C$8 -> 0.15698839
A8: Total | B8: =SUM(B5:B7) -> 19936 | C8: =SUM(C5:C7) -> 22473 | D8: =C8/B8-1 -> 0.12725722 | E8: =SUM(E5:E7) -> 10632 | F8: =SUM(F5:F7) -> 12890 | G8: =F8/E8-1 -> 0.21237773 | H8: =C8/C$8 -> 1
A10: External (non-Humana) services revenue by line
A11: Business line | B11: FY2022 | C11: FY2023 | D11: FY2024 | E11: FY2025 | F11: 1H 2025 | G11: 1H 2026 | H11: FY24→25 %
A12: Pharmacy Solutions | B12: 1025 | C12: 849 | D12: 904 | E12: 1218 | F12: 599 | G12: 679 | H12: =E12/D12-1 -> 0.34734513
A13: Primary Care | B13: 568 | C13: 842 | D13: 1248 | E13: 2197 | F13: 982 | G13: 1627 | H13: =E13/D13-1 -> 0.76041667
A14: Home Solutions | B14: 2333 | C14: 1342 | D14: 1313 | E14: 1401 | F14: 695 | G14: 703 | H14: =E14/D14-1 -> 0.067022087
A15: Total external | B15: =SUM(B12:B14) -> 3926 | C15: =SUM(C12:C14) -> 3033 | D15: =SUM(D12:D14) -> 3465 | E15: =SUM(E12:E14) -> 4816 | F15: =SUM(F12:F14) -> 2276 | G15: =SUM(G12:G14) -> 3009 | H15: =E15/D15-1 -> 0.38989899
A17: Takeaway: primary care external revenue grew ~76% in FY2025 (acquisitions + payer-agnostic growth) — the fastest-growing book of non-Humana payer relationships.

Sheet Spend
A1: Spend Profile
A2: Segment-level costs from Humana consolidating statements; capex & M&A are consolidated Humana figures (not split by segment).
A4: Item ($mm) | B4: FY2024 | C4: FY2025 | D4: 1H 2025 | E4: 1H 2026 | F4: Scope
A5: CenterWell operating costs (excl. D&A) | B5: 18383 | C5: 20915 | D5: 9777 | E5: 12038 | F5: Segment
A6: CenterWell depreciation & amortization | B6: 224 | C6: 219 | D6: 119 | E6: 97 | F6: Segment
A7: CenterWell amortization of intangibles | B7: 43 | C7: 34 | D7: 21 | E7: 11 | F7: Segment
A8: Humana purchases of property & equipment (capex) | B8: 575 | C8: 546 | D8: 209 | E8: 253 | F8: Consolidated
A9: Humana acquisitions, net of cash acquired | B9: 89 | C9: 81 | D9: 1 | E9: 930 | F9: Consolidated (1H26 incl. MaxHealth)
A10: CenterWell total operating expenses | B10: =B5+B6 -> 18607 | C10: =C5+C6 -> 21134 | D10: =D5+D6 -> 9896 | E10: =E5+E6 -> 12135 | F10: Segment
A11: Op. costs as % of segment revenue | B11: =B5/Financials!E5 -> 0.92210072 | C11: =C5/Financials!F5 -> 0.93067236 | D11: =D5/Financials!G5 -> 0.91958239 | E11: =E5/Financials!H5 -> 0.93390225 | F11: Ties to reported operating cost ratio
A13: FY2026 consolidated capex guidance: ~ $650mm. Spend by vendor/category is not publicly disclosed.
A14: Why it matters: ~93% of every revenue dollar is consumed by operating cost — each 10 bps of cost-ratio improvement ≈ $22mm of FY2025 operating income.

Sheet Operating Metrics
A1: Operating Metrics
A2: Source: Humana 4Q25 and 2Q26 statistical supplements.
A4: Primary care | B4: Dec 31, 2024 | C4: Dec 31, 2025 | D4: Jun 30, 2026 | E4: Growth Dec24→Jun26
A5: Centers | B5: 344 | C5: 350 | D5: 398 | E5: =D5/B5-1 -> 0.15697674
A6: Primary care providers | B6: 1002 | C6: 1319 | D6: 1478 | E6: =D6/B6-1 -> 0.4750499
A7: Patients served – total | B7: 390500 | C7: 491100 | D7: 622000 | E7: =D7/B7-1 -> 0.59282971
A8: De novo (WCAS JV) patients | B8: 79400 | C8: 111400 | D8: 137300 | E8: =D8/B8-1 -> 0.72921914
A9: Wholly-owned patients | B9: 246500 | C9: 304900 | D9: 374400 | E9: =D9/B9-1 -> 0.5188641
A10: IPA patients | B10: 64600 | C10: 74800 | D10: 110300 | E10: =D10/B10-1 -> 0.70743034
A12: Home solutions | B12: FY2024 | C12: FY2025 | D12: YoY %
A13: Episodic admissions (PDGM) | B13: 321862 | C13: 315369 | D13: =C13/B13-1 -> -0.020173242
A14: Total admissions – same store | B14: 418603 | C14: 428342 | D14: =C14/B14-1 -> 0.023265481
A16: Pharmacy (Total Medicare) | B16: FY2024 | C16: FY2025 | D16: 1H 2026
A17: Generic dispense rate | B17: 0.91 | C17: 0.905 | D17: 0.908
A18: Mail-order penetration | B18: 0.283 | C18: 0.259 | D18: 0.238
A20: Context: Humana individual Medicare Advantage membership ~6.45mm at Jun 30, 2026 (up ~23% YoY) — the main feeder of CenterWell intersegment volume.

Sheet Affiliated NPIs
A1: Sample of CenterWell-Affiliated Organizational NPIs (Type 2)
A2: CenterWell holds HUNDREDS of NPIs (one per pharmacy, home health branch, clinic subpart). This is a verified sample; pull the full list from the CMS NPPES registry (search org name 'CENTERWELL').
A4: NPI | B4: Legal business name | C4: Business line | D4: Practice city/state | E4: Taxonomy (primary) | F4: Enumerated | G4: Notes
A5: 1235154725 | B5: CENTERWELL PHARMACY, INC. | C5: Pharmacy | D5: West Palm Beach, FL | E5: 3336C0003X Community/Retail Pharmacy | F5: 2006-07-13 | G5: DBA Humana Pharmacy, Inc.
A6: 1215339122 | B6: CENTERWELL PHARMACY, INC. | C6: Pharmacy | D6: Miami, FL | E6: 3336C0003X Community/Retail Pharmacy | F6: 2014-09-23 | G6: DBA PrescribeIt Rx – Kendall
A7: 1013468404 | B7: CENTERWELL PHARMACY, INC. | C7: Pharmacy | D7: Anderson, SC | E7: 3336C0003X Community/Retail Pharmacy | F7: 2016-10-20 | G7: Formerly Humana Pharmacy, Inc.
A8: 1013648195 | B8: CENTERWELL PHARMACY, INC. | C8: Pharmacy | D8: Tampa, FL | E8: 3336C0003X Community/Retail Pharmacy | F8: 2022-06-21
A9: 1063381366 | B9: CENTERWELL PHARMACY, INC. | C9: Pharmacy | D9: West Chester, OH | E9: 3336M0003X Managed Care Org Pharmacy | F9: 2025-11-04
A10: 1306899307 | B10: CENTERWELL SENIOR PRIMARY CARE (FL) INC. | C10: Primary Care | D10: Altamonte Springs, FL | E10: Family/Internal Med/General Practice | F10: 2006-05-18 | G10: Org subpart
A11: 1801002183 | B11: CENTERWELL SENIOR PRIMARY CARE (FL) INC. | C11: Primary Care | D11: Longwood, FL | E11: Family/Internal Med/General Practice | F11: 2007-05-15 | G11: Org subpart
A12: 1508891680 | B12: CENTERWELL SENIOR PRIMARY CARE (FL) INC. | C12: Primary Care | D12: The Villages, FL | E12: Family/Internal Med/General Practice | F12: 2006-07-11 | G12: Org subpart
A13: 1912935008 | B13: CENTERWELL SENIOR PRIMARY CARE (FL) INC. | C13: Primary Care | D13: Orlando, FL | E13: Family/Internal Med/General Practice | F13: 2006-06-29 | G13: Org subpart
A14: 1346293636 | B14: CENTERWELL SENIOR PRIMARY CARE (FL) INC. | C14: Primary Care | D14: Clermont, FL | E14: Family/Internal Med/General Practice | F14: 2006-05-18 | G14: Org subpart
A15: 1194778100 | B15: CENTERWELL SENIOR PRIMARY CARE (FL) INC. | C15: Primary Care | D15: Casselberry, FL | E15: Family/Internal Med/General Practice | F15: 2006-05-19 | G15: Org subpart
A16: 1487680252 | B16: CENTERWELL SENIOR PRIMARY CARE (FL) INC. | C16: Primary Care | D16: Saint Cloud, FL | E16: Family/Internal Med/General Practice | F16: 2006-06-24 | G16: Org subpart
A17: 1003643214 | B17: CENTERWELL SENIOR PRIMARY CARE FL JV PLLC | C17: Primary Care (WCAS JV) | D17: Jacksonville, FL | E17: 207R00000X Internal Medicine | F17: 2024-09-19 | G17: Other name: Conviva Philips Highway
A18: 1609603919 | B18: CENTERWELL SENIOR PRIMARY CARE FL JV PLLC | C18: Primary Care (WCAS JV) | D18: Winter Garden, FL | E18: 207R00000X Internal Medicine | F18: 2024-09-19 | G18: Org subpart
A19: 1306876438 | B19: CENTERWELL CERTIFIED HEALTHCARE CORP. | C19: Home Health | D19: Grand Rapids, MI | E19: Home Health | G19: Mailing: Overland Park, KS
A20: 1558398479 | B20: CENTERWELL CERTIFIED HEALTHCARE CORP. | C20: Home Health | D20: Lincoln, NE | E20: Home Health | G20: Mailing: Overland Park, KS
A21: 1225064934 | B21: CENTERWELL CERTIFIED HEALTHCARE CORP. | C21: Home Health | D21: Racine, WI | E21: Home Health | G21: Mailing: Overland Park, KS
A22: 1548292717 | B22: CENTERWELL CERTIFIED HEALTHCARE CORP. | C22: Home Health | D22: Muncie, IN | E22: Home Health | G22: Mailing: Overland Park, KS
A24: Home-health taxonomy shown generically; verify exact codes in NPPES. Other CenterWell entities to search: CenterWell Specialty Pharmacy, Conviva Care Centers, CenterWell Home Health (state LLCs), The Villages Health, MaxHealth.

Sheet Payment Integrity Play
A1: How a Payment Integrity Vendor Can Help CenterWell Grow
A2: CenterWell is a PROVIDER that increasingly carries payer-like risk. Position PI as margin expansion + revenue protection, not just recovery.
A4: # | B4: Opportunity | C4: CenterWell pain point (evidence) | D4: What we deliver | E4: KPI to promise | F4: Business line
A5: 1 | B5: Downstream claims PI under full-risk capitation | C5: ~64% of Humana individual MA members are in value-based arrangements; CenterWell primary care often takes total-cost-of-care risk for ~622k patients — overpaid specialist/hospital/ancillary claims hit its cost ratio directly. | D5: Pre-pay clinical & coding edits, DRG validation, duplicate/COB checks on claims paid against CenterWell risk pools; post-pay recovery. | E5: Medical cost savings as % of downstream spend; cost-ratio bps | F5: Primary Care
A6: 2 | B6: Risk adjustment accuracy (v28 + RADV readiness) | C6: Humana cites the v28 risk-model phase-in as the main driver of CenterWell's rising cost ratio (93.1% FY25). RADV extrapolation risk is a stated company risk factor. | D6: Two-way HCC chart validation (capture supported gaps, remove unsupported codes), RADV mock audits, provider documentation feedback. | E6: RAF accuracy rate; RADV error rate; revenue protected | F6: Primary Care
A7: 3 | B7: Payer-agnostic underpayment & contract compliance | C7: External primary care revenue +76% in FY25 ($2.2B) as CenterWell signs non-Humana MA plans and acquires groups (Villages Health, MaxHealth). | D7: Contract modeling vs. remits, capitation/shared-savings reconciliation audits with third-party payers, denial overturns. | E7: $ underpayments recovered; days to reconcile; denial overturn % | F7: Primary Care / Home
A8: 4 | B8: Home health billing integrity (PDGM / OASIS) | C8: Episodic admissions fell 2% in FY25 while reimbursement pressure persists; Medicare home health faces ADR, TPE and Review Choice Demonstration audits. | D8: Pre-bill OASIS/PDGM coding QA, LUPA & period-split checks, audit-defense packaging, denial management. | E8: Pre-bill accuracy %; ADR denial rate; DSO | F8: Home Solutions
A9: 5 | B9: Specialty pharmacy reimbursement & audit defense | C9: Specialty volume growth carries a higher cost ratio than traditional pharmacy (cited in FY25 10-K); $13B pharmacy book. | D9: PBM/payer audit defense, NDC-unit & days-supply validation, claim-to-remit reconciliation, manufacturer program reconciliation. | E9: Audit recoupments avoided; net margin per Rx | F9: Pharmacy
A10: 6 | B10: M&A integration billing audits | C10: 1H26 acquisitions spend ~$930mm (incl. MaxHealth); 2025 Villages Health deal added ~32k patients. | D10: Day-1 billing/coding baseline audits of acquired practices, compliance remediation, revenue-cycle harmonization. | E10: Time-to-standard; post-close compliance findings | F10: Primary Care
A13: Illustrative Value Sizing (edit yellow cells)
B14: Driver | C14: Value | D14: Basis / note
B15: FY2025 CenterWell segment revenue ($mm) | C15: =Financials!F5 -> 22473 | D15: Linked to Financials tab
B16: FY2025 primary care revenue ($mm) | C16: ='Revenue by Line'!C6 -> 5986 | D16: Linked
B17: Assumed share of primary care revenue spent on downstream medical claims | C17: 0.7 | D17: ASSUMPTION – validate in discovery
B18: Assumed PI savings rate on downstream claims | C18: 0.01 | D18: ASSUMPTION – typical PI programs 0.5%–2%
B19: Downstream claim savings ($mm) | C19: =C16*C17*C18 -> 41.902 | D19: Formula
B20: FY2025 home solutions revenue ($mm) | C20: ='Revenue by Line'!C7 -> 3528 | D20: Linked
B21: Assumed home-health denial/leakage avoided (% of revenue) | C21: 0.005 | D21: ASSUMPTION
B22: Home health revenue protected ($mm) | C22: =C20*C21 -> 17.64 | D22: Formula
B23: External services revenue FY2025 ($mm) | C23: =Financials!F6 -> 4816 | D23: Linked
B24: Assumed underpayment recovery (% of external revenue) | C24: 0.01 | D24: ASSUMPTION
B25: Underpayments recovered ($mm) | C25: =C23*C24 -> 48.16 | D25: Formula
B26: TOTAL illustrative annual value ($mm) | C26: =C19+C22+C25 -> 107.702 | D26: Formula
B27: Implied operating-cost-ratio improvement (bps) | C27: =C26/C15*10000 -> 47.925066 | D27: Total value ÷ segment revenue
B28: Implied lift to FY2025 IFO | C28: =C26/Financials!F8 -> 0.080434653 | D28: vs $1,339mm GAAP IFO
A31: Pitch line: 'Every 10 bps off CenterWell's ~93% operating cost ratio is worth ~$22mm of operating income — we target that with downstream claims PI, risk-adjustment accuracy and revenue-cycle recovery.'
A32: Assumptions in yellow are illustrative placeholders, not CenterWell disclosures. Replace with discovery data before sharing externally.

Sheet Data Ask & Growth
A1: Data Ask to CenterWell & Growth Analytics (beyond payment integrity)
A2: Ask CenterWell for data on ITS OWN patients. Data on Humana plan members who are not CenterWell patients belongs to Humana Insurance and needs a separate agreement with Humana.
A4: Data to request | B4: Example fields | C4: What we do with it | D4: Simple example | E4: Growth use
A5: 1. Patient & plan mix | B5: Payer, plan type (HMO/PPO/D-SNP), age band, county/ZIP, center, attribution date, disenrollment date | C5: Profile who CenterWell serves and through which plans; spot payer concentration and churn | D5: 78% of patients at a Tampa center are on Humana HMO; D-SNP patients leave twice as often as others | E5: Target non-Humana MA plans for new contracts; build retention outreach for high-churn groups
A6: 2. Value-based care metrics | B6: PMPM cost, MLR, admits & ED visits per 1,000, 30-day readmissions, care-gap / HEDIS & Star measures, shared-savings results by contract | C6: Benchmark each center and contract; find where cost or quality is drifting | D6: Center A's ED visits are 40% above peers, mostly weekend visits for non-urgent issues | E6: Fund weekend urgent slots; use strong quality results to win better contract terms
A7: 3. RAF & risk scores | B7: Patient RAF (v24 vs v28), HCCs captured vs suspected, recapture rate, chart-review outcomes | C7: Find missed or unsupported diagnoses; measure v28 impact by center and doctor | D7: Recapture of chronic conditions is 62% at one clinic vs 85% network-wide | E7: Fix documentation gaps; protect revenue that funds expansion
A8: 4. Claims & payments (from earlier) | B8: 837/835 files, allowed vs paid, provider NPI, DRG, CPT/HCPCS, dates of service | C8: Payment checks, contract compliance, overpayment & underpayment recovery | D8: Same MRI paid twice; Plan X paying $135 instead of contracted $150 | E8: Savings and recoveries improve the cost ratio and free up cash
A10: How this supports CenterWell expansion
A11: Proposal | B11: How data drives it | C11: Simple example
A12: Where to open next centers | B12: Overlay CenterWell patient ZIPs with public CMS county-level Medicare Advantage enrollment to find dense, underserved areas | C12: 3 ZIP codes have 12,000 MA seniors and no CenterWell clinic within 10 miles
A13: Which plans to partner with | B13: Compare outcomes and margin by payer to rank non-Humana plans worth contracting | C13: Plan Y patients are healthier-coded correctly and profitable; pursue a risk contract
A14: Patient retention | B14: Predict which patients may leave based on visits, gaps and plan changes | C14: Flag 900 patients with no visit in 6 months for a care-team call
A15: Doctor / center performance | B15: Rank centers on cost, quality and RAF accuracy | C15: Share best-practice playbook from top-quartile centers
A17: Compliance guardrails
A18: • Signed BAA and data-use agreement listing each purpose (payment integrity, analytics, network planning).
A19: • Use de-identified or aggregated data for expansion and planning analysis wherever possible.
A20: • Do NOT use patient-level data for marketing or 'member attraction' outreach: HIPAA marketing rules generally require patient authorization, and CMS Medicare Advantage marketing rules also apply.
A21: • Frame growth work as network planning and care-access analysis for CenterWell, not as recruiting members for specific plans.
A22: • Have CenterWell's privacy/compliance team approve the data request before it is sent.

Sheet Sources
A1: Sources
A2: All financial data from Humana Inc. public filings; NPI data from public NPPES mirrors.
A4: Data | B4: Source | C4: URL
A5: FY2025 & FY2024 segment results, revenue by line, spend, metrics | B5: Humana 4Q25 earnings release (Feb 11, 2026) | C5: https://humana.gcs-web.com/static-files/5e60f4bf-c568-4ad2-8181-19db72780d71
A6: 1H2026 results, FY2026 guidance, Jun-2026 metrics | B6: Humana 2Q26 earnings release, Form 8-K Ex. 99.2 (Jul 29, 2026) | C6: https://www.sec.gov/Archives/edgar/data/0000049071/000004907126000045/hum-2026q2xex99x2detailedx.htm
A7: FY2025 external services by line, cost-ratio drivers | B7: Humana Form 10-K FY2025 | C7: https://www.sec.gov/Archives/edgar/data/49071/000004907126000009/hum-20251231.htm
A8: FY2023 & FY2022 segment results | B8: Humana Form 10-K FY2023 | C8: https://www.sec.gov/Archives/edgar/data/49071/000004907124000012/hum-20231231.htm
A9: FY2022 & FY2021 segment results | B9: Humana Annual Report FY2022 | C9: https://www.sec.gov/Archives/edgar/data/49071/000119312523063816/d448361dars.pdf
A10: Brand launch, logo meaning | B10: Humana press release, Mar 16, 2021 | C10: https://humana.gcs-web.com/node/33566
A11: Brand statement; home health & pharmacy rebrand | B11: Business Wire, Sep 1, 2022 | C11: https://www.businesswire.com/news/home/20220901005209/en
A12: NPI records | B12: NPPES mirrors: npiviewer.com, npiprofile.com, npiindex.com, stedi.com | C12: https://npiregistry.cms.hhs.gov/
